ecoscape_layers/__init__.py
ecoscape_layers/constants.py
ecoscape_layers/layers.py
ecoscape_layers/redlist.py
ecoscape_layers/utils.py
ecoscape_layers-0.0.12.dist-info/LICENSE.md
ecoscape_layers-0.0.12.dist-info/METADATA
ecoscape_layers-0.0.12.dist-info/WHEEL
ecoscape_layers-0.0.12.dist-info/entry_points.txt
ecoscape_layers-0.0.12.dist-info/top_level.txt
ecoscape_layers-0.0.12.dist-info/RECORD
