Metadata-Version: 2.1
Name: ecoscape-layers
Version: 0.0.12
Summary: EcoScape habitat and matrix layer creation
Author-email: Jasmine Tai <cjtai@ucsc.edu>, Ian Holloway <imhollow@ucsc.edu>, Aadity Sharma <ashar115@ucsc.edu>, Coen Adler <ctadler@ucsc.edu>, Luca de Alfaro <luca@ucsc.edu>, Artie Nazarov <anazarov@ucsc.edu>, Natalia Ocampo-Peñuela <nocampop@ucsc.edu>, Natalie Valett <nvalett@ucsc.edu>
Project-URL: Homepage, https://github.com/ecoscape-earth/ecoscape-layers
Project-URL: Bug Tracker, https://github.com/ecoscape-earth/ecoscape-layers/issues
Classifier: Programming Language :: Python :: 3
Classifier: License :: OSI Approved :: BSD License
Classifier: Operating System :: OS Independent
Requires-Python: >=3.7
License-File: LICENSE.md
Requires-Dist: ebird-api >=3.0.0
Requires-Dist: fiona >=1.8.22
Requires-Dist: gdal >=3.0.0
Requires-Dist: numpy >=1.20.0
Requires-Dist: pyproj >=2.6.1
Requires-Dist: rasterio >=1.2.10
Requires-Dist: Requests >=2.28.1
Requires-Dist: scgt >=0.0.6
Requires-Dist: Shapely >=1.8.4
Requires-Dist: tqdm >=4.66.4
Requires-Dist: psutil >=5.9.8
Requires-Dist: pandas >=2.2.2
